utils.py
web_server_scanner.py
cli/cli_wrapper.py
ip_scanner_project-1.0.0.dist-info/METADATA
ip_scanner_project-1.0.0.dist-info/WHEEL
ip_scanner_project-1.0.0.dist-info/entry_points.txt
ip_scanner_project-1.0.0.dist-info/top_level.txt
ip_scanner_project-1.0.0.dist-info/RECORD
