Metadata-Version: 2.1
Name: ip-scanner-project
Version: 1.0.0
Summary: Provides an IP scanner library and CLI wrapper. Checks if given IP addresses match specified software (nginx and IIS) and versions, and if they have a directory listing available at the root directory. Wrapper can be ran with ip-scanner-project-cli --ips <ip> <ip>
Author: Barton Elles
Requires-Dist: requests (==2.31.0)
Requires-Dist: termcolor (==2.3.0)
